{
  "6709737146": [
    {
      "orderId": "TRX-mcqcgk99-1UFQYXYH",
      "awaitingCustomDeposit": true,
      "isPackagePurchase": true,
      "timestamp": 1751726047205
    },
    {
      "orderId": "TRX-mcqcfn8s-PD833STP",
      "koin": 1500000,
      "days": 0,
      "messageId": 15259,
      "awaitingCustomDeposit": false,
      "isPackagePurchase": false,
      "timestamp": 1751726063132
    },
    {
      "orderId": "TRX-mcqcfn8s-PD833STP",
      "koin": 5000,
      "days": 0,
      "messageId": 15249,
      "awaitingCustomDeposit": false,
      "isPackagePurchase": false,
      "timestamp": 1751726065385,
      "adminMessageId": 15260
    },
    {
      "orderId": "TRX-mcqcj0qo-CPXDQQHQ",
      "awaitingCustomDeposit": true,
      "isPackagePurchase": true,
      "timestamp": 1751726162150
    },
    {
      "orderId": "TRX-mcqcfn8s-PD833STP",
      "koin": 150000,
      "days": 0,
      "messageId": 15267,
      "awaitingCustomDeposit": false,
      "isPackagePurchase": false,
      "timestamp": 1751726175668
    },
    {
      "orderId": "TRX-mcqcfn8s-PD833STP",
      "awaitingCustomDeposit": true,
      "isPackagePurchase": false,
      "timestamp": 1751726177818,
      "adminMessageId": 15268
    }
  ]
}