{
  "6709737146": [
    {
      "orderId": "TRX-mcqboq21-BECQWD3T",
      "koin": 1000,
      "messageId": 15184,
      "awaitingCustomDeposit": false,
      "timestamp": 1751724759666
    },
    {
      "orderId": "TRX-mcqboq21-BECQWD3T",
      "awaitingCustomDeposit": true,
      "timestamp": 1751724761445,
      "adminMessageId": 15185
    },
    {
      "orderId": "TRX-mcqbr5d7-R7M5OI2B",
      "awaitingCustomDeposit": true,
      "timestamp": 1751724861504
    },
    {
      "orderId": "TRX-mcqboq21-BECQWD3T",
      "koin": 150000,
      "messageId": 15195,
      "awaitingCustomDeposit": false,
      "timestamp": 1751724866855
    },
    {
      "orderId": "TRX-mcqboq21-BECQWD3T",
      "koin": 1000,
      "messageId": 15184,
      "awaitingCustomDeposit": false,
      "timestamp": 1751724868645,
      "adminMessageId": 15196
    }
  ]
}